litemodel_cli/__init__.py
litemodel_cli/__main__.py
litemodel_cli/project_structure.py
litemodel_cli/artifacts/admin.py
litemodel_cli/artifacts/admin_views.py
litemodel_cli/artifacts/app.py
litemodel_cli/artifacts/event_handlers.py
litemodel_cli/artifacts/jinja_filters.py
litemodel_cli/artifacts/middleware.py
litemodel_cli/artifacts/models.py
litemodel_cli/artifacts/resources.py
litemodel_cli/artifacts/routes.py
litemodel_cli/artifacts/settings.py
litemodel_cli/artifacts/static/css/bootstrap.min.css
litemodel_cli/artifacts/static/js/bootstrap.min.js
litemodel_cli/artifacts/static/js/htmx.min.js
litemodel_cli/artifacts/templates/_admin_base.html
litemodel_cli/artifacts/templates/_admin_footer.html
litemodel_cli/artifacts/templates/_admin_header.hml
litemodel_cli/artifacts/templates/admin_detail.html
litemodel_cli/artifacts/templates/admin_edit.html
litemodel_cli/artifacts/templates/admin_index.html
litemodel_cli/artifacts/templates/admin_list.html
litemodel_cli/artifacts/templates/admin_login.html
litemodel_cli/artifacts/templates/admin_logout.html
litemodel_cli/artifacts/templates/admin_new.html
litemodel_cli-0.1.4.dist-info/METADATA
litemodel_cli-0.1.4.dist-info/WHEEL
litemodel_cli-0.1.4.dist-info/entry_points.txt
litemodel_cli-0.1.4.dist-info/RECORD
