Metadata-Version: 2.4
Name: litemodel-cli
Version: 0.1.4
Summary: CLI for managing litemodel-starlette apps
Author-email: Joe Pasquantonio <joe.pasquantonio@gmail.com>
Requires-Python: >=3.11
Requires-Dist: typer>=0.15.1
